README.rst
setup.cfg
setup.py
casper/__init__.py
casper/info.py
casper.egg-info/PKG-INFO
casper.egg-info/SOURCES.txt
casper.egg-info/dependency_links.txt
casper.egg-info/requires.txt
casper.egg-info/top_level.txt
casper/demo/__init__.py
casper/demo/module.py
casper/lib/__init__.py
casper/lib/base/__init__.py
casper/lib/base/observable.py
casper/lib/base/observable_list.py
casper/lib/base/topological_sort.py
casper/lib/base/xmltodict.py
casper/lib/controls/__init__.py
casper/lib/controls/base.py
casper/lib/controls/directory.py
casper/lib/controls/enum.py
casper/lib/controls/file.py
casper/lib/controls/float.py
casper/lib/controls/int.py
casper/lib/controls/list.py
casper/lib/controls/object.py
casper/lib/controls/string.py
casper/pipeline/__init__.py
casper/pipeline/bbox.py
casper/pipeline/ibox.py
casper/pipeline/link_parser.py
casper/pipeline/pbox.py
casper/pipeline/utils.py
casper/view/__init__.py
casper/view/colors.py
casper/view/pipeline_viewer.py