Metadata-Version: 1.1
Name: casper
Version: 1.0.0
Summary: CASPER
Home-page: UNKNOWN
Author: CASPER developers
Author-email: antoine.grigis@cea.fr
License: CeCILL-B
Platform: OS Independent
Classifier: Development Status :: 5 - Production/Stable
Classifier: Environment :: Console
Classifier: Environment :: X11 Applications :: Qt
Classifier: Operating System :: OS Independent
Classifier: Programming Language :: Python
Classifier: Topic :: Scientific/Engineering
Classifier: Topic :: Utilities
